<?xml version="1.0" encoding="utf-8"?>
<!DOCTYPE hibernate-mapping PUBLIC "-//Hibernate/Hibernate Mapping DTD 3.0//EN"
"http://hibernate.sourceforge.net/hibernate-mapping-3.0.dtd">
<!-- 
    Mapping file autogenerated by MyEclipse Persistence Tools
-->
<hibernate-mapping>
    <class name="com.hrm.entity.StoreGoodsClear" table="store_goods_clear">
        <composite-id name="id" class="com.hrm.entity.StoreGoodsClearId">
            <key-property name="cleardate" type="java.util.Date">
                <column name="cleardate" length="0" />
            </key-property>
            <key-property name="goodsid" type="java.lang.String">
                <column name="goodsid" length="50" />
            </key-property>
            <key-property name="userlist" type="java.lang.String">
                <column name="userlist" length="50" />
            </key-property>
        </composite-id>
        <property name="sstorenumber" type="java.lang.Integer">
            <column name="sstorenumber">
                <comment>śłÖÁģóŤ°®ÁĽüŤģ°ÁöĄŚļďŚ≠ėśēįťáŹ</comment>
            </column>
        </property>
        <property name="soutnumber" type="java.lang.Integer">
            <column name="soutnumber">
                <comment>śłÖÁģóŤ°®ÁĽüŤģ°ÁöĄŚáļŚĒģśēįťáŹ</comment>
            </column>
        </property>
        <property name="sreturnnumber" type="java.lang.Integer">
            <column name="sreturnnumber">
                <comment>śłÖÁģóŤ°®ÁĽüŤģ°ÁöĄťÄÄŤīßśēįťáŹ</comment>
            </column>
        </property>
        <property name="slastnumber" type="java.lang.Integer">
            <column name="slastnumber">
                <comment>śłÖÁģóŤ°®ÁĽüŤģ°ÁöĄŚČ©šĹôśēįťáŹ</comment>
            </column>
        </property>
        <property name="gstorenumber" type="java.lang.Integer">
            <column name="gstorenumber">
                <comment>goods_listÁöĄŚļďŚ≠ėśēįťáŹ</comment>
            </column>
        </property>
        <property name="goutnumber" type="java.lang.Integer">
            <column name="goutnumber">
                <comment>goods_listÁöĄŚáļŚĒģśēįťáŹ</comment>
            </column>
        </property>
        <property name="greturnnumber" type="java.lang.Integer">
            <column name="greturnnumber">
                <comment>goods_listÁöĄťÄÄŤīßśēįťáŹ</comment>
            </column>
        </property>
        <property name="glastnumber" type="java.lang.Integer">
            <column name="glastnumber">
                <comment>goods_listÁöĄŚČ©šĹôśēįťáŹ</comment>
            </column>
        </property>
        <property name="equals" type="java.lang.String">
            <column name="equals" length="2">
                <comment>śėĮŚź¶ÁõłÁ≠Č (ŤīĘŚä°Śģ°śČĻ,ťÖíśįīśĮĒŚĮĻ) 0=šłćÁ≠Č 1=ÁõłÁ≠Č</comment>
            </column>
        </property>
        <property name="updtuser" type="java.lang.String">
            <column name="updtuser" length="50">
                <comment>śõīśĖįšļļ</comment>
            </column>
        </property>
        <property name="updttime" type="java.util.Date">
            <column name="updttime" length="0" />
        </property>
    </class>
</hibernate-mapping>
